{
  "raw_html": "<button type='button' role='link' class='btn btn-link p-0 text-start' id='link_2' aria-label=\" Kousik Das & Ors. versus State of West Bengal & Ors. pdf\"  class='noToken' href='#' onclick=javascript:open_pdf('2','2025','2025_4_695_713','2025INSC448'); ><font size='4'> <strong>KOUSIK DAS & ORS.<span class='fst-italic'> versus </span>STATE OF WEST BENGAL & ORS. </strong>- <span class='escrText'>[2025] 4 S.C.R. 695</span><span class='ncDisplay'>2025 INSC 448</span><input type='hidden' id='cnr' value=ESCR010004802025></button></font><br><strong>Coram : BHUSHAN RAMKRISHNA GAVAI<sup style=\"color: #268e97;font-size: 22px;top: 0;\" class=\"tooltip-sup\" data-tooltip=\"Author\">*</sup>, AUGUSTINE GEORGE MASIH</strong><br> Issue for Consideration Whether in light of the judgment of this Court in the case of Jaiveer Singh &amp; Ors. v. The State of Uttarakhand &amp; Ors. and the order of this Court in the case of Viswanath v. The State of Uttarakhand &amp; Ors. the impugned judgment and order of the High Court is Headnotes&dagger; Right of Children to Free and Compulsory Education Act, 2009 &ndash; s.23 &ndash; NCTE (Recognition, Norms and Procedure) Regulations, 2014 &ndash; A notification dated 29.09.2022 was issued by the WBBPE for the recruitment of qualified trained candidates to the posts of<br><strong class='caseDetailsTD' ><span style='color:#212F3D' > Decision Date :</span><font color='green'> 04-04-2025</font><span style='color:#212F3D' > | Case No :</span><font color='green'> CIVIL APPEAL No. 4963/2025</font><span style='color:#212F3D' > | Disposal Nature :</span><font color='green'> Appeal(s) allowed</font>   <span style='color:#212F3D' > |  Bench :</span><font color='green'> 2 Judges</font></strong><div class='row my-1 mt-2 border bg-light'><div class='col-auto'><a href='#' class='btn btn-outline-secondary btn-sm my-1' onclick=open_splitview('2','2025','2025_4_695_713','2025INSC448','S')><i <i class='fas fa-columns me-2'></i>Split view</a></div><div class='col-auto'><a href='#' class='btn btn-outline-secondary btn-sm my-1' onclick=open_splitview('2','2025','2025_4_695_713','2025INSC448','H'); ><i class='fas fa-file-alt me-2'></i>HTML view</a></div><div class='col-auto'><a href='#' class='btn btn-outline-secondary btn-sm my-1' onclick=open_flip('2','2025','2025_4_695_713','2025INSC448');><i class='fas fa-book-open me-2' ></i>Flip view</a></div><div class='col-auto'><a href='#' class='btn btn-outline-secondary btn-sm my-1' onclick=open_pdf('2','2025','2025_4_695_713','2025INSC448','N'); ><i class='fas fa-file-pdf me-2'></i>PDF</a></div></div>",
  "path": "2025_4_695_713",
  "citation_year": "2025",
  "nc_display": "2025INSC448",
  "scraped_at": "2026-02-11T06:34:49.928747"
}