{
  "raw_html": "<button type='button' role='link' class='btn btn-link p-0 text-start' id='link_10' aria-label=\" State by Deputy Superintendent of Police versus B.T. Ramesh & Anr. pdf\"  class='noToken' href='#' onclick=javascript:open_pdf('10','2025','2025_8_202_220','2025INSC840'); ><font size='4'> <strong>STATE BY DEPUTY SUPERINTENDENT OF POLICE<span class='fst-italic'> versus </span>B.T. RAMESH & ANR. </strong>- <span class='escrText'>[2025] 8 S.C.R. 202</span><span class='ncDisplay'>2025 INSC 840</span><input type='hidden' id='cnr' value=ESCR010003132025></button></font><br><strong>Coram : DIPANKAR DATTA<sup style=\"color: #268e97;font-size: 22px;top: 0;\" class=\"tooltip-sup\" data-tooltip=\"Author\">*</sup>, MANMOHAN</strong><br> Issue for Consideration Issue arose whether the High Court was justified in quashing the criminal proceedings, on the grounds of the chargesheet having been filed more than four years after the date of the alleged incident and lack of sanction; and whether r.214 of the Karnataka Civil any application to stifle criminal proceedings for offences punishable under the IPC or the PC Act or any analogous law. Headnotes&dagger; Code of Criminal Procedure, 1973 &ndash; ss.197, 482 &ndash; Prevention of Corruption Act, 1988 &ndash; Karnataka Civil Services Rules, 1958 &ndash; r.214<br><strong class='caseDetailsTD' ><span style='color:#212F3D' > Decision Date :</span><font color='green'> 14-07-2025</font><span style='color:#212F3D' > | Case No :</span><font color='green'> CIVIL APPEAL No. 9463/2025</font><span style='color:#212F3D' > | Disposal Nature :</span><font color='green'> Case Partly allowed</font>   <span style='color:#212F3D' > |  Bench :</span><font color='green'> 2 Judges</font></strong><div class='row my-1 mt-2 border bg-light'><div class='col-auto'><a href='#' class='btn btn-outline-secondary btn-sm my-1' onclick=open_splitview('10','2025','2025_8_202_220','2025INSC840','S')><i <i class='fas fa-columns me-2'></i>Split view</a></div><div class='col-auto'><a href='#' class='btn btn-outline-secondary btn-sm my-1' onclick=open_splitview('10','2025','2025_8_202_220','2025INSC840','H'); ><i class='fas fa-file-alt me-2'></i>HTML view</a></div><div class='col-auto'><a href='#' class='btn btn-outline-secondary btn-sm my-1' onclick=open_flip('10','2025','2025_8_202_220','2025INSC840');><i class='fas fa-book-open me-2' ></i>Flip view</a></div><div class='col-auto'><a href='#' class='btn btn-outline-secondary btn-sm my-1' onclick=open_pdf('10','2025','2025_8_202_220','2025INSC840','N'); ><i class='fas fa-file-pdf me-2'></i>PDF</a></div></div>",
  "path": "2025_8_202_220",
  "citation_year": "2025",
  "nc_display": "2025INSC840",
  "scraped_at": "2025-10-22T07:47:14.771505"
}