{
  "raw_html": "<button type='button' role='link' class='btn btn-link p-0 text-start' id='link_1' aria-label=\" Jaipur Vidyut Vitaran Nigam Limited and Ors. versus Rajasthan Textile Mills Association & Anr. Etc. pdf\"  class='noToken' href='#' onclick=javascript:open_pdf('1','2025','2025_4_2028_2044','2025INSC592'); ><font size='4'> <strong>JAIPUR VIDYUT VITARAN NIGAM LIMITED AND ORS.<span class='fst-italic'> versus </span>RAJASTHAN TEXTILE MILLS ASSOCIATION & ANR. ETC. </strong>- <span class='escrText'>[2025] 4 S.C.R. 2028</span><span class='ncDisplay'>2025 INSC 592</span><input type='hidden' id='cnr' value=ESCR010005542025></button></font><br><strong>Coram : ABHAY S. OKA<sup style=\"color: #268e97;font-size: 22px;top: 0;\" class=\"tooltip-sup\" data-tooltip=\"Author\">*</sup>, AUGUSTINE GEORGE MASIH</strong><br> Issue for Consideration Issue relates to the determination of the Cross-Subsidy Surcharges by the Rajasthan Electricity Regulatory Commission (State Commission). Headnotes&dagger; Electricity Act, 2003 &ndash; s.42(2) &ndash; Rajasthan Electricity and Conditions for Determination of Tariff) Regulations, 2014 &ndash; Regulations 90, 2(a)(60) &ndash; Cross-Subsidy Surcharge (CSS) &ndash; Determination of: Held: The CSS has to be determined based on the prevailing tariff rates &ndash; Neither the 2003 Act nor the 2014 Regulations makes the<br><strong class='caseDetailsTD' ><span style='color:#212F3D' > Decision Date :</span><font color='green'> 29-04-2025</font><span style='color:#212F3D' > | Case No :</span><font color='green'> CIVIL APPEAL No. 8862/2022</font><span style='color:#212F3D' > | Disposal Nature :</span><font color='green'> Appeal(s) allowed</font>   <span style='color:#212F3D' > |  Bench :</span><font color='green'> 2 Judges</font></strong><div class='row my-1 mt-2 border bg-light'><div class='col-auto'><a href='#' class='btn btn-outline-secondary btn-sm my-1' onclick=open_splitview('1','2025','2025_4_2028_2044','2025INSC592','S')><i <i class='fas fa-columns me-2'></i>Split view</a></div><div class='col-auto'><a href='#' class='btn btn-outline-secondary btn-sm my-1' onclick=open_splitview('1','2025','2025_4_2028_2044','2025INSC592','H'); ><i class='fas fa-file-alt me-2'></i>HTML view</a></div><div class='col-auto'><a href='#' class='btn btn-outline-secondary btn-sm my-1' onclick=open_flip('1','2025','2025_4_2028_2044','2025INSC592');><i class='fas fa-book-open me-2' ></i>Flip view</a></div><div class='col-auto'><a href='#' class='btn btn-outline-secondary btn-sm my-1' onclick=open_pdf('1','2025','2025_4_2028_2044','2025INSC592','N'); ><i class='fas fa-file-pdf me-2'></i>PDF</a></div></div>",
  "path": "2025_4_2028_2044",
  "citation_year": "2025",
  "nc_display": "2025INSC592",
  "scraped_at": "2026-02-11T06:35:51.106610"
}