{
  "raw_html": "<button type='button' role='link' class='btn btn-link p-0 text-start' id='link_4' aria-label=\" K. Prabhakar Hegde versus Bank of Baroda pdf\"  class='noToken' href='#' onclick=javascript:open_pdf('4','2025','2025_8_1997_2049','2025INSC997'); ><font size='4'> <strong>K. PRABHAKAR HEGDE<span class='fst-italic'> versus </span>BANK OF BARODA </strong>- <span class='escrText'>[2025] 8 S.C.R. 1997</span><span class='ncDisplay'>2025 INSC 997</span><input type='hidden' id='cnr' value=ESCR010007562025></button></font><br><strong>Coram : DIPANKAR DATTA<sup style=\"color: #268e97;font-size: 22px;top: 0;\" class=\"tooltip-sup\" data-tooltip=\"Author\">*</sup>, PRASHANT KUMAR MISHRA</strong><br> Issue for Consideration (i) Whether denial of the report of preliminary inquiry prepared by the officer entrusted by Vijaya Bank (which merged with the respondent in the year 2019) to conduct such inquiry, who happened to be the sole management witness, was sufficient to vitiate the regular (ii) whether the failure/omission of the Inquiry Officer to generally question the appellant on the circumstances appearing against him in the evidence, as per Regulation 6(17) of the Vijaya Bank Officer Employees&rsquo; (Discipline and Appeal) Regulations, 1981, vitiated the inquiry;<br><strong class='caseDetailsTD' ><span style='color:#212F3D' > Decision Date :</span><font color='green'> 19-08-2025</font><span style='color:#212F3D' > | Case No :</span><font color='green'> CIVIL APPEAL No. 6599/2025</font><span style='color:#212F3D' > | Disposal Nature :</span><font color='green'> Disposed off</font>   <span style='color:#212F3D' > |  Bench :</span><font color='green'> 2 Judges</font></strong><div class='row my-1 mt-2 border bg-light'><div class='col-auto'><a href='#' class='btn btn-outline-secondary btn-sm my-1' onclick=open_splitview('4','2025','2025_8_1997_2049','2025INSC997','S')><i <i class='fas fa-columns me-2'></i>Split view</a></div><div class='col-auto'><a href='#' class='btn btn-outline-secondary btn-sm my-1' onclick=open_splitview('4','2025','2025_8_1997_2049','2025INSC997','H'); ><i class='fas fa-file-alt me-2'></i>HTML view</a></div><div class='col-auto'><a href='#' class='btn btn-outline-secondary btn-sm my-1' onclick=open_flip('4','2025','2025_8_1997_2049','2025INSC997');><i class='fas fa-book-open me-2' ></i>Flip view</a></div><div class='col-auto'><a href='#' class='btn btn-outline-secondary btn-sm my-1' onclick=open_pdf('4','2025','2025_8_1997_2049','2025INSC997','N'); ><i class='fas fa-file-pdf me-2'></i>PDF</a></div></div>",
  "path": "2025_8_1997_2049",
  "citation_year": "2025",
  "nc_display": "2025INSC997",
  "scraped_at": "2026-02-11T06:38:39.732764"
}