{
  "raw_html": "<button type='button' role='link' class='btn btn-link p-0 text-start' id='link_3' aria-label=\" Baljinder Kumar @ Kala versus State of Punjab pdf\"  class='noToken' href='#' onclick=javascript:open_pdf('3','2025','2025_7_1070_1103','2025INSC856'); ><font size='4'> <strong>BALJINDER KUMAR @ KALA<span class='fst-italic'> versus </span>STATE OF PUNJAB </strong>- <span class='escrText'>[2025] 7 S.C.R. 1070</span><span class='ncDisplay'>2025 INSC 856</span><input type='hidden' id='cnr' value=ESCR010007862025></button></font><br><strong>Coram : VIKRAM NATH<sup style=\"color: #268e97;font-size: 22px;top: 0;\" class=\"tooltip-sup\" data-tooltip=\"Author\">*</sup>, SANJAY KAROL, SANDEEP MEHTA</strong><br> Issue for Consideration Whether the courts below erred in convicting the appellant for offences u/ss.302, 308 and 325, Penal Code, 1860 and imposing death sentence on him, when the prosecution had failed to prove his guilt beyond reasonable doubt. Headnotes&dagger; Evidence &ndash; Charges not doubt &ndash; Courts below strongly relying upon the testimonies of three witnesses PW1 (the complainant), PW2 (alleged eyewitness) and PW17 (injured child witness), convicted the appellant for the murder of his wife, two children and sister-in-law and imposed death sentence &ndash;<br><strong class='caseDetailsTD' ><span style='color:#212F3D' > Decision Date :</span><font color='green'> 16-07-2025</font><span style='color:#212F3D' > | Case No :</span><font color='green'> CRIMINAL APPEAL No. 2688/2024</font><span style='color:#212F3D' > | Disposal Nature :</span><font color='green'> Appeal(s) allowed</font>   <span style='color:#212F3D' > |  Bench :</span><font color='green'> 3 Judges</font></strong><div class='row my-1 mt-2 border bg-light'><div class='col-auto'><a href='#' class='btn btn-outline-secondary btn-sm my-1' onclick=open_splitview('3','2025','2025_7_1070_1103','2025INSC856','S')><i <i class='fas fa-columns me-2'></i>Split view</a></div><div class='col-auto'><a href='#' class='btn btn-outline-secondary btn-sm my-1' onclick=open_splitview('3','2025','2025_7_1070_1103','2025INSC856','H'); ><i class='fas fa-file-alt me-2'></i>HTML view</a></div><div class='col-auto'><a href='#' class='btn btn-outline-secondary btn-sm my-1' onclick=open_flip('3','2025','2025_7_1070_1103','2025INSC856');><i class='fas fa-book-open me-2' ></i>Flip view</a></div><div class='col-auto'><a href='#' class='btn btn-outline-secondary btn-sm my-1' onclick=open_pdf('3','2025','2025_7_1070_1103','2025INSC856','N'); ><i class='fas fa-file-pdf me-2'></i>PDF</a></div></div>",
  "path": "2025_7_1070_1103",
  "citation_year": "2025",
  "nc_display": "2025INSC856",
  "scraped_at": "2026-04-11T19:26:03.083071"
}